MANIFEST.in
board_project_view.xml
project_data.xml
project_demo.xml
project_view.xml
res_config_view.xml
res_partner_view.xml
setup.py
./__init__.py
./__openerp__.py
./company.py
./project.py
./res_config.py
./res_partner.py
./report/__init__.py
./report/project_report.py
./wizard/__init__.py
./wizard/project_task_delegate.py
./wizard/project_task_reevaluate.py
i18n/ar.po
i18n/bg.po
i18n/bs.po
i18n/ca.po
i18n/cs.po
i18n/da.po
i18n/de.po
i18n/el.po
i18n/es.po
i18n/es_AR.po
i18n/es_CO.po
i18n/es_CR.po
i18n/es_EC.po
i18n/es_MX.po
i18n/es_PY.po
i18n/es_VE.po
i18n/et.po
i18n/eu.po
i18n/fi.po
i18n/fr.po
i18n/gl.po
i18n/gu.po
i18n/he.po
i18n/hr.po
i18n/hu.po
i18n/id.po
i18n/it.po
i18n/ja.po
i18n/ko.po
i18n/lt.po
i18n/lv.po
i18n/mk.po
i18n/mn.po
i18n/nb.po
i18n/nl.po
i18n/nl_BE.po
i18n/pl.po
i18n/project.pot
i18n/pt.po
i18n/pt_BR.po
i18n/ro.po
i18n/ru.po
i18n/sk.po
i18n/sl.po
i18n/sq.po
i18n/sv.po
i18n/th.po
i18n/tlh.po
i18n/tr.po
i18n/uk.po
i18n/vi.po
i18n/zh_CN.po
i18n/zh_TW.po
images/gantt.png
images/project-hover.png
images/project.jpeg
images/project.png
images/project_dashboard.jpeg
images/project_kanban.jpeg
images/project_task.jpeg
images/project_task_tree.jpeg
images/task_analysis.jpeg
images/task_kanban.jpeg
images/task_stages.jpeg
openerp_project.egg-info/PKG-INFO
openerp_project.egg-info/SOURCES.txt
openerp_project.egg-info/dependency_links.txt
openerp_project.egg-info/requires.txt
openerp_project.egg-info/top_level.txt
process/task_process.xml
report/project_cumulative.xml
report/project_report.xml
report/project_report.xsl
report/project_report_view.xml
security/ir.model.access.csv
security/project_security.xml
static/src/img/icon.png
static/src/img/tasks_icon.png
static/src/js/project.js
test/project_demo.yml
test/project_process.yml
test/task_process.yml
wizard/project_task_delegate_view.xml
wizard/project_task_reevaluate_view.xml